Workbook

Sheet MONTHLY_INPUT
A1: EMPLOYEE NAME | B1: BASIC SALARY | C1: INCLUDE TRANSPORT (1/0) | D1: TRANSPORT RATE % | E1: TRANSPORT OVERRIDE | F1: INCLUDE UTILITY (1/0) | G1: UTILITY RATE % | H1: UTILITY OVERRIDE | I1: INCLUDE RENT (1/0) | J1: RENT RATE % | K1: RENT OVERRIDE | L1: INCLUDE RISK (1/0) | M1: RISK RATE % | N1: RISK OVERRIDE | O1: INCLUDE LEAVE (1/0) | P1: LEAVE RATE % | Q1: LEAVE OVERRIDE | R1: INCLUDE CLOTHING (1/0) | S1: CLOTHING RATE % | T1: CLOTHING OVERRIDE | U1: OTHER EARNINGS | V1: OVERTIME ADDITION | W1: WELFARE FUND | X1: UNION DUES | Y1: PMSU/GMWU SUPPORT | Z1: LATENESS DEDUCTION | AA1: ABSENTEEISM DEDUCTION | AB1: LOAN AMOUNT | AC1: TOTAL PAID (LOAN) | AD1: TRANSPORT AMOUNT | AE1: UTILITY AMOUNT | AF1: RENT AMOUNT | AG1: RISK AMOUNT | AH1: LEAVE AMOUNT | AI1: CLOTHING AMOUNT | AJ1: PROVIDENT EARNING (3.5%) | AK1: PROVIDENT EARNING (6.5%) | AL1: GROSS EARNINGS | AM1: SOCIAL SECURITY (5.5%) | AN1: PROVIDENT DEDUCTION (3.5%) | AO1: PROVIDENT DEDUCTION (16.5%) | AP1: TAXABLE INCOME | AQ1: PAYE | AR1: TOTAL DEDUCTIONS | AS1: NET SALARY | AT1: OUTSTANDING LOAN
A2: Ama Owusu | B2: 20000 | C2: 1 | D2: 25 | F2: 1 | G2: 15 | I2: 1 | J2: 20 | L2: 1 | M2: 10 | O2: 0 | P2: 100 | R2: 0 | S2: 0 | AD2: =IF(C2=0,0,IF(E2="",B2*D2/100,E2)) | AE2: =IF(F2=0,0,IF(H2="",B2*G2/100,H2)) | AF2: =IF(I2=0,0,IF(K2="",B2*J2/100,K2)) | AG2: =IF(L2=0,0,IF(N2="",B2*M2/100,N2)) | AH2: =IF(O2=0,0,IF(Q2="",B2*P2/100,Q2)) | AI2: =IF(R2=0,0,IF(T2="",B2*S2/100,T2)) | AJ2: =B2*0.035 | AK2: =B2*0.065 | AL2: =SUM(B2,AD2,AE2,AF2,AG2,AH2,AI2,U2,V2,AJ2,AK2) | AM2: =B2*0.055 | AN2: =B2*0.035 | AO2: =B2*0.165 | AP2: =MAX(0,AL2-AM2-AO2) | AQ2: =IF(AP2<=490,0,IF(AP2<=600,(AP2-490)*0.05,IF(AP2<=730,5.5+(AP2-600)*0.10,IF(AP2<=3896.67,18.5+(AP2-730)*0.175,IF(AP2<=19896.67,572.67+(AP2-3896.67)*0.25,IF(AP2<=50416.67,4572.67+(AP2-19896.67)*0.30,13728.67+(AP2-50416.67)*0.35)))))) | AR2: =SUM(AM2,AQ2,W2,X2,Y2,Z2,AA2,AN2,AO2) | AS2: =AL2-AR2 | AT2: =AB2-AC2
AD3: =IF(C3=0,0,IF(E3="",B3*D3/100,E3)) | AE3: =IF(F3=0,0,IF(H3="",B3*G3/100,H3)) | AF3: =IF(I3=0,0,IF(K3="",B3*J3/100,K3)) | AG3: =IF(L3=0,0,IF(N3="",B3*M3/100,N3)) | AH3: =IF(O3=0,0,IF(Q3="",B3*P3/100,Q3)) | AI3: =IF(R3=0,0,IF(T3="",B3*S3/100,T3)) | AJ3: =B3*0.035 | AK3: =B3*0.065 | AL3: =SUM(B3,AD3,AE3,AF3,AG3,AH3,AI3,U3,V3,AJ3,AK3) | AM3: =B3*0.055 | AN3: =B3*0.035 | AO3: =B3*0.165 | AP3: =MAX(0,AL3-AM3-AO3) | AQ3: =IF(AP3<=490,0,IF(AP3<=600,(AP3-490)*0.05,IF(AP3<=730,5.5+(AP3-600)*0.10,IF(AP3<=3896.67,18.5+(AP3-730)*0.175,IF(AP3<=19896.67,572.67+(AP3-3896.67)*0.25,IF(AP3<=50416.67,4572.67+(AP3-19896.67)*0.30,13728.67+(AP3-50416.67)*0.35)))))) | AR3: =SUM(AM3,AQ3,W3,X3,Y3,Z3,AA3,AN3,AO3) | AS3: =AL3-AR3 | AT3: =AB3-AC3
AD4: =IF(C4=0,0,IF(E4="",B4*D4/100,E4)) | AE4: =IF(F4=0,0,IF(H4="",B4*G4/100,H4)) | AF4: =IF(I4=0,0,IF(K4="",B4*J4/100,K4)) | AG4: =IF(L4=0,0,IF(N4="",B4*M4/100,N4)) | AH4: =IF(O4=0,0,IF(Q4="",B4*P4/100,Q4)) | AI4: =IF(R4=0,0,IF(T4="",B4*S4/100,T4)) | AJ4: =B4*0.035 | AK4: =B4*0.065 | AL4: =SUM(B4,AD4,AE4,AF4,AG4,AH4,AI4,U4,V4,AJ4,AK4) | AM4: =B4*0.055 | AN4: =B4*0.035 | AO4: =B4*0.165 | AP4: =MAX(0,AL4-AM4-AO4) | AQ4: =IF(AP4<=490,0,IF(AP4<=600,(AP4-490)*0.05,IF(AP4<=730,5.5+(AP4-600)*0.10,IF(AP4<=3896.67,18.5+(AP4-730)*0.175,IF(AP4<=19896.67,572.67+(AP4-3896.67)*0.25,IF(AP4<=50416.67,4572.67+(AP4-19896.67)*0.30,13728.67+(AP4-50416.67)*0.35)))))) | AR4: =SUM(AM4,AQ4,W4,X4,Y4,Z4,AA4,AN4,AO4) | AS4: =AL4-AR4 | AT4: =AB4-AC4
AD5: =IF(C5=0,0,IF(E5="",B5*D5/100,E5)) | AE5: =IF(F5=0,0,IF(H5="",B5*G5/100,H5)) | AF5: =IF(I5=0,0,IF(K5="",B5*J5/100,K5)) | AG5: =IF(L5=0,0,IF(N5="",B5*M5/100,N5)) | AH5: =IF(O5=0,0,IF(Q5="",B5*P5/100,Q5)) | AI5: =IF(R5=0,0,IF(T5="",B5*S5/100,T5)) | AJ5: =B5*0.035 | AK5: =B5*0.065 | AL5: =SUM(B5,AD5,AE5,AF5,AG5,AH5,AI5,U5,V5,AJ5,AK5) | AM5: =B5*0.055 | AN5: =B5*0.035 | AO5: =B5*0.165 | AP5: =MAX(0,AL5-AM5-AO5) | AQ5: =IF(AP5<=490,0,IF(AP5<=600,(AP5-490)*0.05,IF(AP5<=730,5.5+(AP5-600)*0.10,IF(AP5<=3896.67,18.5+(AP5-730)*0.175,IF(AP5<=19896.67,572.67+(AP5-3896.67)*0.25,IF(AP5<=50416.67,4572.67+(AP5-19896.67)*0.30,13728.67+(AP5-50416.67)*0.35)))))) | AR5: =SUM(AM5,AQ5,W5,X5,Y5,Z5,AA5,AN5,AO5) | AS5: =AL5-AR5 | AT5: =AB5-AC5
AD6: =IF(C6=0,0,IF(E6="",B6*D6/100,E6)) | AE6: =IF(F6=0,0,IF(H6="",B6*G6/100,H6)) | AF6: =IF(I6=0,0,IF(K6="",B6*J6/100,K6)) | AG6: =IF(L6=0,0,IF(N6="",B6*M6/100,N6)) | AH6: =IF(O6=0,0,IF(Q6="",B6*P6/100,Q6)) | AI6: =IF(R6=0,0,IF(T6="",B6*S6/100,T6)) | AJ6: =B6*0.035 | AK6: =B6*0.065 | AL6: =SUM(B6,AD6,AE6,AF6,AG6,AH6,AI6,U6,V6,AJ6,AK6) | AM6: =B6*0.055 | AN6: =B6*0.035 | AO6: =B6*0.165 | AP6: =MAX(0,AL6-AM6-AO6) | AQ6: =IF(AP6<=490,0,IF(AP6<=600,(AP6-490)*0.05,IF(AP6<=730,5.5+(AP6-600)*0.10,IF(AP6<=3896.67,18.5+(AP6-730)*0.175,IF(AP6<=19896.67,572.67+(AP6-3896.67)*0.25,IF(AP6<=50416.67,4572.67+(AP6-19896.67)*0.30,13728.67+(AP6-50416.67)*0.35)))))) | AR6: =SUM(AM6,AQ6,W6,X6,Y6,Z6,AA6,AN6,AO6) | AS6: =AL6-AR6 | AT6: =AB6-AC6
AD7: =IF(C7=0,0,IF(E7="",B7*D7/100,E7)) | AE7: =IF(F7=0,0,IF(H7="",B7*G7/100,H7)) | AF7: =IF(I7=0,0,IF(K7="",B7*J7/100,K7)) | AG7: =IF(L7=0,0,IF(N7="",B7*M7/100,N7)) | AH7: =IF(O7=0,0,IF(Q7="",B7*P7/100,Q7)) | AI7: =IF(R7=0,0,IF(T7="",B7*S7/100,T7)) | AJ7: =B7*0.035 | AK7: =B7*0.065 | AL7: =SUM(B7,AD7,AE7,AF7,AG7,AH7,AI7,U7,V7,AJ7,AK7) | AM7: =B7*0.055 | AN7: =B7*0.035 | AO7: =B7*0.165 | AP7: =MAX(0,AL7-AM7-AO7) | AQ7: =IF(AP7<=490,0,IF(AP7<=600,(AP7-490)*0.05,IF(AP7<=730,5.5+(AP7-600)*0.10,IF(AP7<=3896.67,18.5+(AP7-730)*0.175,IF(AP7<=19896.67,572.67+(AP7-3896.67)*0.25,IF(AP7<=50416.67,4572.67+(AP7-19896.67)*0.30,13728.67+(AP7-50416.67)*0.35)))))) | AR7: =SUM(AM7,AQ7,W7,X7,Y7,Z7,AA7,AN7,AO7) | AS7: =AL7-AR7 | AT7: =AB7-AC7
AD8: =IF(C8=0,0,IF(E8="",B8*D8/100,E8)) | AE8: =IF(F8=0,0,IF(H8="",B8*G8/100,H8)) | AF8: =IF(I8=0,0,IF(K8="",B8*J8/100,K8)) | AG8: =IF(L8=0,0,IF(N8="",B8*M8/100,N8)) | AH8: =IF(O8=0,0,IF(Q8="",B8*P8/100,Q8)) | AI8: =IF(R8=0,0,IF(T8="",B8*S8/100,T8)) | AJ8: =B8*0.035 | AK8: =B8*0.065 | AL8: =SUM(B8,AD8,AE8,AF8,AG8,AH8,AI8,U8,V8,AJ8,AK8) | AM8: =B8*0.055 | AN8: =B8*0.035 | AO8: =B8*0.165 | AP8: =MAX(0,AL8-AM8-AO8) | AQ8: =IF(AP8<=490,0,IF(AP8<=600,(AP8-490)*0.05,IF(AP8<=730,5.5+(AP8-600)*0.10,IF(AP8<=3896.67,18.5+(AP8-730)*0.175,IF(AP8<=19896.67,572.67+(AP8-3896.67)*0.25,IF(AP8<=50416.67,4572.67+(AP8-19896.67)*0.30,13728.67+(AP8-50416.67)*0.35)))))) | AR8: =SUM(AM8,AQ8,W8,X8,Y8,Z8,AA8,AN8,AO8) | AS8: =AL8-AR8 | AT8: =AB8-AC8
AD9: =IF(C9=0,0,IF(E9="",B9*D9/100,E9)) | AE9: =IF(F9=0,0,IF(H9="",B9*G9/100,H9)) | AF9: =IF(I9=0,0,IF(K9="",B9*J9/100,K9)) | AG9: =IF(L9=0,0,IF(N9="",B9*M9/100,N9)) | AH9: =IF(O9=0,0,IF(Q9="",B9*P9/100,Q9)) | AI9: =IF(R9=0,0,IF(T9="",B9*S9/100,T9)) | AJ9: =B9*0.035 | AK9: =B9*0.065 | AL9: =SUM(B9,AD9,AE9,AF9,AG9,AH9,AI9,U9,V9,AJ9,AK9) | AM9: =B9*0.055 | AN9: =B9*0.035 | AO9: =B9*0.165 | AP9: =MAX(0,AL9-AM9-AO9) | AQ9: =IF(AP9<=490,0,IF(AP9<=600,(AP9-490)*0.05,IF(AP9<=730,5.5+(AP9-600)*0.10,IF(AP9<=3896.67,18.5+(AP9-730)*0.175,IF(AP9<=19896.67,572.67+(AP9-3896.67)*0.25,IF(AP9<=50416.67,4572.67+(AP9-19896.67)*0.30,13728.67+(AP9-50416.67)*0.35)))))) | AR9: =SUM(AM9,AQ9,W9,X9,Y9,Z9,AA9,AN9,AO9) | AS9: =AL9-AR9 | AT9: =AB9-AC9
AD10: =IF(C10=0,0,IF(E10="",B10*D10/100,E10)) | AE10: =IF(F10=0,0,IF(H10="",B10*G10/100,H10)) | AF10: =IF(I10=0,0,IF(K10="",B10*J10/100,K10)) | AG10: =IF(L10=0,0,IF(N10="",B10*M10/100,N10)) | AH10: =IF(O10=0,0,IF(Q10="",B10*P10/100,Q10)) | AI10: =IF(R10=0,0,IF(T10="",B10*S10/100,T10)) | AJ10: =B10*0.035 | AK10: =B10*0.065 | AL10: =SUM(B10,AD10,AE10,AF10,AG10,AH10,AI10,U10,V10,AJ10,AK10) | AM10: =B10*0.055 | AN10: =B10*0.035 | AO10: =B10*0.165 | AP10: =MAX(0,AL10-AM10-AO10) | AQ10: =IF(AP10<=490,0,IF(AP10<=600,(AP10-490)*0.05,IF(AP10<=730,5.5+(AP10-600)*0.10,IF(AP10<=3896.67,18.5+(AP10-730)*0.175,IF(AP10<=19896.67,572.67+(AP10-3896.67)*0.25,IF(AP10<=50416.67,4572.67+(AP10-19896.67)*0.30,13728.67+(AP10-50416.67)*0.35)))))) | AR10: =SUM(AM10,AQ10,W10,X10,Y10,Z10,AA10,AN10,AO10) | AS10: =AL10-AR10 | AT10: =AB10-AC10
AD11: =IF(C11=0,0,IF(E11="",B11*D11/100,E11)) | AE11: =IF(F11=0,0,IF(H11="",B11*G11/100,H11)) | AF11: =IF(I11=0,0,IF(K11="",B11*J11/100,K11)) | AG11: =IF(L11=0,0,IF(N11="",B11*M11/100,N11)) | AH11: =IF(O11=0,0,IF(Q11="",B11*P11/100,Q11)) | AI11: =IF(R11=0,0,IF(T11="",B11*S11/100,T11)) | AJ11: =B11*0.035 | AK11: =B11*0.065 | AL11: =SUM(B11,AD11,AE11,AF11,AG11,AH11,AI11,U11,V11,AJ11,AK11) | AM11: =B11*0.055 | AN11: =B11*0.035 | AO11: =B11*0.165 | AP11: =MAX(0,AL11-AM11-AO11) | AQ11: =IF(AP11<=490,0,IF(AP11<=600,(AP11-490)*0.05,IF(AP11<=730,5.5+(AP11-600)*0.10,IF(AP11<=3896.67,18.5+(AP11-730)*0.175,IF(AP11<=19896.67,572.67+(AP11-3896.67)*0.25,IF(AP11<=50416.67,4572.67+(AP11-19896.67)*0.30,13728.67+(AP11-50416.67)*0.35)))))) | AR11: =SUM(AM11,AQ11,W11,X11,Y11,Z11,AA11,AN11,AO11) | AS11: =AL11-AR11 | AT11: =AB11-AC11
AD12: =IF(C12=0,0,IF(E12="",B12*D12/100,E12)) | AE12: =IF(F12=0,0,IF(H12="",B12*G12/100,H12)) | AF12: =IF(I12=0,0,IF(K12="",B12*J12/100,K12)) | AG12: =IF(L12=0,0,IF(N12="",B12*M12/100,N12)) | AH12: =IF(O12=0,0,IF(Q12="",B12*P12/100,Q12)) | AI12: =IF(R12=0,0,IF(T12="",B12*S12/100,T12)) | AJ12: =B12*0.035 | AK12: =B12*0.065 | AL12: =SUM(B12,AD12,AE12,AF12,AG12,AH12,AI12,U12,V12,AJ12,AK12) | AM12: =B12*0.055 | AN12: =B12*0.035 | AO12: =B12*0.165 | AP12: =MAX(0,AL12-AM12-AO12) | AQ12: =IF(AP12<=490,0,IF(AP12<=600,(AP12-490)*0.05,IF(AP12<=730,5.5+(AP12-600)*0.10,IF(AP12<=3896.67,18.5+(AP12-730)*0.175,IF(AP12<=19896.67,572.67+(AP12-3896.67)*0.25,IF(AP12<=50416.67,4572.67+(AP12-19896.67)*0.30,13728.67+(AP12-50416.67)*0.35)))))) | AR12: =SUM(AM12,AQ12,W12,X12,Y12,Z12,AA12,AN12,AO12) | AS12: =AL12-AR12 | AT12: =AB12-AC12
AD13: =IF(C13=0,0,IF(E13="",B13*D13/100,E13)) | AE13: =IF(F13=0,0,IF(H13="",B13*G13/100,H13)) | AF13: =IF(I13=0,0,IF(K13="",B13*J13/100,K13)) | AG13: =IF(L13=0,0,IF(N13="",B13*M13/100,N13)) | AH13: =IF(O13=0,0,IF(Q13="",B13*P13/100,Q13)) | AI13: =IF(R13=0,0,IF(T13="",B13*S13/100,T13)) | AJ13: =B13*0.035 | AK13: =B13*0.065 | AL13: =SUM(B13,AD13,AE13,AF13,AG13,AH13,AI13,U13,V13,AJ13,AK13) | AM13: =B13*0.055 | AN13: =B13*0.035 | AO13: =B13*0.165 | AP13: =MAX(0,AL13-AM13-AO13) | AQ13: =IF(AP13<=490,0,IF(AP13<=600,(AP13-490)*0.05,IF(AP13<=730,5.5+(AP13-600)*0.10,IF(AP13<=3896.67,18.5+(AP13-730)*0.175,IF(AP13<=19896.67,572.67+(AP13-3896.67)*0.25,IF(AP13<=50416.67,4572.67+(AP13-19896.67)*0.30,13728.67+(AP13-50416.67)*0.35)))))) | AR13: =SUM(AM13,AQ13,W13,X13,Y13,Z13,AA13,AN13,AO13) | AS13: =AL13-AR13 | AT13: =AB13-AC13
AD14: =IF(C14=0,0,IF(E14="",B14*D14/100,E14)) | AE14: =IF(F14=0,0,IF(H14="",B14*G14/100,H14)) | AF14: =IF(I14=0,0,IF(K14="",B14*J14/100,K14)) | AG14: =IF(L14=0,0,IF(N14="",B14*M14/100,N14)) | AH14: =IF(O14=0,0,IF(Q14="",B14*P14/100,Q14)) | AI14: =IF(R14=0,0,IF(T14="",B14*S14/100,T14)) | AJ14: =B14*0.035 | AK14: =B14*0.065 | AL14: =SUM(B14,AD14,AE14,AF14,AG14,AH14,AI14,U14,V14,AJ14,AK14) | AM14: =B14*0.055 | AN14: =B14*0.035 | AO14: =B14*0.165 | AP14: =MAX(0,AL14-AM14-AO14) | AQ14: =IF(AP14<=490,0,IF(AP14<=600,(AP14-490)*0.05,IF(AP14<=730,5.5+(AP14-600)*0.10,IF(AP14<=3896.67,18.5+(AP14-730)*0.175,IF(AP14<=19896.67,572.67+(AP14-3896.67)*0.25,IF(AP14<=50416.67,4572.67+(AP14-19896.67)*0.30,13728.67+(AP14-50416.67)*0.35)))))) | AR14: =SUM(AM14,AQ14,W14,X14,Y14,Z14,AA14,AN14,AO14) | AS14: =AL14-AR14 | AT14: =AB14-AC14
... AD1001: =IF(C1001=0,0,IF(E1001="",B1001*D1001/100,E1001)) | AE1001: =IF(F1001=0,0,IF(H1001="",B1001*G1001/100,H1001)) | AF1001: =IF(I1001=0,0,IF(K1001="",B1001*J1001/100,K1001)) | AG1001: =IF(L1001=0,0,IF(N1001="",B1001*M1001/100,N1001)) | AH1001: =IF(O1001=0,0,IF(Q1001="",B1001*P1001/100,Q1001)) | AI1001: =IF(R1001=0,0,IF(T1001="",B1001*S1001/100,T1001)) | AJ1001: =B1001*0.035 | AK1001: =B1001*0.065 | AL1001: =SUM(B1001,AD1001,AE1001,AF1001,AG1001,AH1001,AI1001,U1001,V1001,AJ1001,AK1001) | AM1001: =B1001*0.055 | AN1001: =B1001*0.035 | AO1001: =B1001*0.165 | AP1001: =MAX(0,AL1001-AM1001-AO1001) | AQ1001: =IF(AP1001<=490,0,IF(AP1001<=600,(AP1001-490)*0.05,IF(AP1001<=730,5.5+(AP1001-600)*0.10,IF(AP1001<=3896.67,18.5+(AP1001-730)*0.175,IF(AP1001<=19896.67,572.67+(AP1001-3896.67)*0.25,IF(AP1001<=50416.67,4572.67+(AP1001-19896.67)*0.30,13728.67+(AP1001-50416.67)*0.35)))))) | AR1001: =SUM(AM1001,AQ1001,W1001,X1001,Y1001,Z1001,AA1001,AN1001,AO1001) | AS1001: =AL1001-AR1001 | AT1001: =AB1001-AC1001

Sheet SUMMARY
A1: GB MONTHLY PAYROLL SUMMARY
A3: TOTAL EMPLOYEES | B3: =COUNTA(MONTHLY_INPUT!A2:A1001)
A4: TOTAL GROSS EARNINGS | B4: =SUM(MONTHLY_INPUT!AL2:AL1001)
A5: TOTAL TAXABLE INCOME | B5: =SUM(MONTHLY_INPUT!AP2:AP1001)
A6: TOTAL PAYE | B6: =SUM(MONTHLY_INPUT!AQ2:AQ1001)
A7: TOTAL DEDUCTIONS | B7: =SUM(MONTHLY_INPUT!AR2:AR1001)
A8: TOTAL NET SALARY | B8: =SUM(MONTHLY_INPUT!AS2:AS1001)
A9: TOTAL OUTSTANDING LOAN | B9: =SUM(MONTHLY_INPUT!AT2:AT1001)

Sheet PAYE_BANDS
A1: BAND | B1: RANGE (GHS) | C1: RATE | D1: BAND TAX | E1: CUMULATIVE TAX
A2: 1 | B2: 0.00 - 490.00 | C2: 0% | D2: 0 | E2: 0
A3: 2 | B3: 490.01 - 600.00 | C3: 5% | D3: 5.5 | E3: 5.5
A4: 3 | B4: 600.01 - 730.00 | C4: 10% | D4: 13 | E4: 18.5
A5: 4 | B5: 730.01 - 3,896.67 | C5: 17.5% | D5: 554.17 | E5: 572.67
A6: 5 | B6: 3,896.68 - 19,896.67 | C6: 25% | D6: 4000 | E6: 4572.67
A7: 6 | B7: 19,896.68 - 50,416.67 | C7: 30% | D7: 9156 | E7: 13728.67
A8: 7 | B8: 50,416.68 and above | C8: 35%

Sheet README
A1: HOW TO USE
A3: 1. Open MONTHLY_INPUT sheet.
A4: 2. Enter employee name and basic salary.
A5: 3. Use include columns as 1 (include) or 0 (exclude).
A6: 4. Keep override cells blank for auto-calculation from rates.
A7: 5. Fill welfare/union/support/lateness/absenteeism/loan values if needed.
A8: 6. All PAYE and totals calculate automatically.
A9: 7. View totals in SUMMARY sheet.
